Workbook

Sheet Leia-me
B2: LEGAL HEALTH
B3: Valuation Atualizado + Projeção de Receita (10 anos) — 3 Cenários
B4: Documento de apoio à decisão — não é laudo de avaliação nem promessa de resultado financeiro
B6: O QUE MUDOU NESTA VERSÃO
B7: O valuation (Berkus + Scorecard) foi atualizado incorporando a validação positiva dos 10 médicos
B8: embaixadores — isso elevou os critérios de 'Execução inicial' e 'Tração' em relação à primeira versão.
B9: Foi adicionada uma projeção de receita (ARR) para 10 anos, em 3 cenários, e uma aba que traduz
B10: essa receita futura em valuation projetado, usando múltiplos de ARR por estágio.
B11: COMO USAR
B12: 1. Edite apenas as células em AZUL sobre fundo amarelo — são os únicos inputs do modelo.
B13: 2. Abas 'Berkus' e 'Scorecard': valuation de HOJE, sem receita (método padrão pré-seed).
B14: 3. Aba 'Projeção de Receita': número de clientes e ticket médio (ARPU) por ano, para cada cenário.
... B30: Gerado em 24/07/2026 — Legal Health · Inteligência Jurídica para Medicina

Sheet Resumo Executivo
B2: RESUMO EXECUTIVO
B3: Legal Health — valuation atual e trajetória projetada de receita e valuation (10 anos)
B5: VALUATION DE HOJE (PRÉ-LANÇAMENTO)
B6: Método | C6: Valuation pré-money
B7: Berkus Method | C7: =Berkus!D12 -> 1165000
B8: Scorecard Method | C8: =Scorecard!E19 -> 1737000
B10: FAIXA DEFENSÁVEL (±25% da média) | C10: =AVERAGE(C7:C8)*0.75 -> 1088250 | D10: =AVERAGE(C7:C8)*1.25 -> 1813750
B12: Ponto médio: | C12: =AVERAGE(C7:C8) -> 1451000
B15: RECEITA PROJETADA (ARR) — 3 CENÁRIOS
C16: Ano 1 | D16: Ano 3 | E16: Ano 5 | F16: Ano 7 | G16: Ano 10
B17: Conservador | C17: ='Projeção de Receita'!D12 -> 201600 | D17: ='Projeção de Receita'!F12 -> 4998400 | E17: ='Projeção de Receita'!H12 -> 13000000 | F17: ='Projeção de Receita'!J12 -> 22002000 | G17: ='Projeção de Receita'!M12 -> 38001600
B18: Moderado | C18: ='Projeção de Receita'!D17 -> 1000800 | D18: ='Projeção de Receita'!F17 -> 8998000 | E18: ='Projeção de Receita'!H17 -> 28002000 | F18: ='Projeção de Receita'!J17 -> 55002000 | G18: ='Projeção de Receita'!M17 -> 100000800
B19: Otimista | C19: ='Projeção de Receita'!D22 -> 1800000 | D19: ='Projeção de Receita'!F22 -> 17001600 | E19: ='Projeção de Receita'!H22 -> 55000400 | F19: ='Projeção de Receita'!J22 -> 115002000 | G19: ='Projeção de Receita'!M22 -> 249998400
B22: VALUATION PROJETADO (ARR × MÚLTIPLO)
C23: Ano 1 | D23: Ano 3 | E23: Ano 5 | F23: Ano 7 | G23: Ano 10
B24: Conservador | C24: ='Valuation Projetado'!C11 -> 1612800 | D24: ='Valuation Projetado'!D11 -> 34988800 | E24: ='Valuation Projetado'!E11 -> 78000000 | F24: ='Valuation Projetado'!F11 -> 121011000 | G24: ='Valuation Projetado'!G11 -> 190008000
B25: Moderado | C25: ='Valuation Projetado'!C15 -> 8006400 | D25: ='Valuation Projetado'!D15 -> 62986000 | E25: ='Valuation Projetado'!E15 -> 168012000 | F25: ='Valuation Projetado'!F15 -> 302511000 | G25: ='Valuation Projetado'!G15 -> 500004000
B26: Otimista | C26: ='Valuation Projetado'!C19 -> 14400000 | D26: ='Valuation Projetado'!D19 -> 119011200 | E26: ='Valuation Projetado'!E19 -> 330002400 | F26: ='Valuation Projetado'!F19 -> 632511000 | G26: ='Valuation Projetado'!G19 -> 1249992000
B29: Leia as abas 'Berkus', 'Scorecard', 'Projeção de Receita' e 'Valuation Projetado' para editar as premissas
B30: por trás de cada número. Projeções de 10 anos são cenários, não previsões — trate como ferramenta de
B31: planejamento, não como garantia.

Sheet Berkus
B2: MÉTODO BERKUS — ATUALIZADO
B3: Startups pré-receita — valor por critério de risco superado (teto de referência: R$ 500 mil/critério)
B5: Critério de risco | C5: Valor atribuído | D5: Justificativa
B6: Ideia sólida (Sound Idea) | C6: 350000 | D6: Mercado real (judicialização da saúde), dor validada, produto nomeado (Juriscore®).
B7: Protótipo / redução de risco tecnológico | C7: 400000 | D7: MVP 2.0 funcional: dashboard, Juriscore®, redator de peças, jurimetria, OCR de documentos — todos operantes com IA real.
B8: Qualidade e histórico da equipe | C8: 150000 | D8: Fundador com formação jurídica + advogado doutor em Direito Constitucional + programador + gestores de tráfego/projeto. Eleve se houver exit ou execução prévia comprovada.
B9: Relacionamentos estratégicos | C9: 100000 | D9: 10 médicos embaixadores engajados. Eleve com parceria formal (associação médica, seguradora, escritório de advocacia).
B10: Execução inicial / lançamento no mercado | C10: 165000 | D10: ATUALIZADO: validação qualitativa positiva de médicos embaixadores testando o produto. Ainda sem cliente pagante — eleve significativamente no 1º contrato pago.
B12: VALUATION PRÉ-MONEY (BERKUS) | D12: =SUM(C6:C10) -> 1165000

Sheet Scorecard
B2: MÉTODO SCORECARD — ATUALIZADO
B3: Compara a startup à média de pré-seed do setor, ajustada por fatores de comparação
B5: Valuation pré-money médio — pré-seed SaaS vertical B2B, Brasil, sem receita | E5: 1800000
B8: Fator de comparação | C8: Peso | D8: Sua nota | E8: Contribuição | F8: Como calibrar
B9: Força da equipe / fundadores | C9: 0.3 | D9: 0.85 | E9: =C9*D9 -> 0.255 | F9: 1.5 = time c/ exit ou sênior comprovado; 1.0 = média; 0.5 = primeira empreitada sem rede.
B10: Tamanho da oportunidade (TAM/SAM/SOM) | C10: 0.25 | D10: 1.1 | E10: =C10*D10 -> 0.275 | F10: TAM > R$10bi sustenta nota >1.0; reduza se o SOM realista for pequeno.
B11: Produto / tecnologia (IA) | C11: 0.15 | D11: 1.15 | E11: =C11*D11 -> 0.1725 | F11: MVP 2.0 com 6 módulos de IA operantes está acima da média de pré-seed.
B12: Tração inicial (usuários, waitlist, receita) | C12: 0.1 | D12: 0.9 | E12: =C12*D12 -> 0.09 | F12: ATUALIZADO: validação positiva de 10 médicos eleva a nota, mas ainda não há cliente pagante (por isso <1.0).
B13: Parcerias e canais estratégicos | C13: 0.1 | D13: 0.7 | E13: =C13*D13 -> 0.07 | F13: Sem parceria formalizada com escritório, CRM ou seguradora ainda.
B14: Necessidade de capital adicional | C14: 0.05 | D14: 1 | E14: =C14*D14 -> 0.05 | F14: Neutro por padrão; ajuste se a estrutura de captação já estiver definida.
B15: Outros fatores (timing, regulação de IA) | C15: 0.05 | D15: 1.05 | E15: =C15*D15 -> 0.0525 | F15: Judicialização da saúde em alta e IA jurídica em voga favorecem o timing.
B17: MULTIPLICADOR SCORECARD (soma ponderada) | E17: =SUM(E9:E15) -> 0.965
B19: VALUATION PRÉ-MONEY (SCORECARD) | E19: =E5*E17 -> 1737000

Sheet Projeção de Receita
B2: PROJEÇÃO DE RECEITA — 10 ANOS
B3: 3 cenários (Conservador · Moderado · Otimista) — edite clientes e ticket médio; a receita recalcula sozinha
C5: Hoje | D5: Ano 1 | E5: Ano 2 | F5: Ano 3 | G5: Ano 4 | H5: Ano 5 | I5: Ano 6 | J5: Ano 7 | K5: Ano 8 | L5: Ano 9 | M5: Ano 10
B6: Ticket médio anual — ARPU (R$) | D6: 3600 | E6: 4000 | F6: 4400 | G6: 4800 | H6: 5200 | I6: 5600 | J6: 6000 | K6: 6400 | L6: 6800 | M6: 7200
B7: Premissa: mix de planos migra de Essential para Professional/Enterprise ao longo do tempo.
B9: CENÁRIO CONSERVADOR
B10: Clientes ativos | C10: 0 | D10: 56 | E10: 300 | F10: 1136 | G10: 1667 | H10: 2500 | I10: 3036 | J10: 3667 | K10: 4219 | L10: 4706 | M10: 5278
B11: Crescimento anual de clientes | E11: =IFERROR(E10/D10-1,"") -> 4.3571429 | F11: =IFERROR(F10/E10-1,"") -> 2.7866667 | G11: =IFERROR(G10/F10-1,"") -> 0.46742958 | H11: =IFERROR(H10/G10-1,"") -> 0.49970006 | I11: =IFERROR(I10/H10-1,"") -> 0.2144 | J11: =IFERROR(J10/I10-1,"") -> 0.20783926 | K11: =IFERROR(K10/J10-1,"") -> 0.15053177 | L11: =IFERROR(L10/K10-1,"") -> 0.1154302 | M11: =IFERROR(M10/L10-1,"") -> 0.12154696
B12: ARR — Receita Recorrente Anual (R$) | C12: 0 | D12: =D10*D6 -> 201600 | E12: =E10*E6 -> 1200000 | F12: =F10*F6 -> 4998400 | G12: =G10*G6 -> 8001600 | H12: =H10*H6 -> 13000000 | I12: =I10*I6 -> 17001600 | J12: =J10*J6 -> 22002000 | K12: =K10*K6 -> 27001600 | ... M12: =M10*M6 -> 38001600
B14: CENÁRIO MODERADO
B15: Clientes ativos | C15: 0 | D15: 278 | E15: 875 | F15: 2045 | G15: 3542 | H15: 5385 | I15: 6786 | J15: 9167 | K15: 10938 | L15: 12500 | M15: 13889
B16: Crescimento anual de clientes | E16: =IFERROR(E15/D15-1,"") -> 2.147482 | F16: =IFERROR(F15/E15-1,"") -> 1.3371429 | G16: =IFERROR(G15/F15-1,"") -> 0.73202934 | H16: =IFERROR(H15/G15-1,"") -> 0.5203275 | I16: =IFERROR(I15/H15-1,"") -> 0.26016713 | J16: =IFERROR(J15/I15-1,"") -> 0.35086944 | K16: =IFERROR(K15/J15-1,"") -> 0.19319297 | L16: =IFERROR(L15/K15-1,"") -> 0.1428049 | M16: =IFERROR(M15/L15-1,"") -> 0.11112
B17: ARR — Receita Recorrente Anual (R$) | C17: 0 | D17: =D15*D6 -> 1000800 | E17: =E15*E6 -> 3500000 | F17: =F15*F6 -> 8998000 | G17: =G15*G6 -> 17001600 | H17: =H15*H6 -> 28002000 | I17: =I15*I6 -> 38001600 | J17: =J15*J6 -> 55002000 | K17: =K15*K6 -> 70003200 | ... M17: =M15*M6 -> 100000800
B19: CENÁRIO OTIMISTA
B20: Clientes ativos | C20: 0 | D20: 500 | E20: 1500 | F20: 3864 | G20: 6667 | H20: 10577 | I20: 14286 | J20: 19167 | K20: 25000 | L20: 29412 | M20: 34722
B21: Crescimento anual de clientes | E21: =IFERROR(E20/D20-1,"") -> 2 | F21: =IFERROR(F20/E20-1,"") -> 1.576 | G21: =IFERROR(G20/F20-1,"") -> 0.72541408 | H21: =IFERROR(H20/G20-1,"") -> 0.58647068 | I21: =IFERROR(I20/H20-1,"") -> 0.35066654 | J21: =IFERROR(J20/I20-1,"") -> 0.34166317 | K21: =IFERROR(K20/J20-1,"") -> 0.30432514 | L21: =IFERROR(L20/K20-1,"") -> 0.17648 | M21: =IFERROR(M20/L20-1,"") -> 0.18053856
B22: ARR — Receita Recorrente Anual (R$) | C22: 0 | D22: =D20*D6 -> 1800000 | E22: =E20*E6 -> 6000000 | F22: =F20*F6 -> 17001600 | G22: =G20*G6 -> 32001600 | H22: =H20*H6 -> 55000400 | I22: =I20*I6 -> 80001600 | J22: =J20*J6 -> 115002000 | K22: =K20*K6 -> 160000000 | ... M22: =M20*M6 -> 249998400

Sheet Valuation Projetado
B2: VALUATION PROJETADO
B3: Traduz a receita futura (aba anterior) em valuation estimado, aplicando um múltiplo sobre o ARR
C5: Ano 1 | D5: Ano 3 | E5: Ano 5 | F5: Ano 7 | G5: Ano 10
B6: Múltiplo de ARR aplicado | C6: 8 | D6: 7 | E6: 6 | F6: 5.5 | G6: 5
B7: Referência: 7-9x em rodadas de alto crescimento; 5-6x em estágio de maturação; 4-5x em exits/growth tardio.
B9: CENÁRIO CONSERVADOR
B10: ARR projetado (R$) | C10: ='Projeção de Receita'!D12 -> 201600 | D10: ='Projeção de Receita'!F12 -> 4998400 | E10: ='Projeção de Receita'!H12 -> 13000000 | F10: ='Projeção de Receita'!J12 -> 22002000 | G10: ='Projeção de Receita'!M12 -> 38001600
B11: Valuation implícito (ARR × múltiplo) | C11: =C10*C6 -> 1612800 | D11: =D10*D6 -> 34988800 | E11: =E10*E6 -> 78000000 | F11: =F10*F6 -> 121011000 | G11: =G10*G6 -> 190008000
B13: CENÁRIO MODERADO
B14: ARR projetado (R$) | C14: ='Projeção de Receita'!D17 -> 1000800 | D14: ='Projeção de Receita'!F17 -> 8998000 | E14: ='Projeção de Receita'!H17 -> 28002000 | F14: ='Projeção de Receita'!J17 -> 55002000 | G14: ='Projeção de Receita'!M17 -> 100000800
B15: Valuation implícito (ARR × múltiplo) | C15: =C14*C6 -> 8006400 | D15: =D14*D6 -> 62986000 | E15: =E14*E6 -> 168012000 | F15: =F14*F6 -> 302511000 | G15: =G14*G6 -> 500004000
B17: CENÁRIO OTIMISTA
B18: ARR projetado (R$) | C18: ='Projeção de Receita'!D22 -> 1800000 | D18: ='Projeção de Receita'!F22 -> 17001600 | E18: ='Projeção de Receita'!H22 -> 55000400 | F18: ='Projeção de Receita'!J22 -> 115002000 | G18: ='Projeção de Receita'!M22 -> 249998400
B19: Valuation implícito (ARR × múltiplo) | C19: =C18*C6 -> 14400000 | D19: =D18*D6 -> 119011200 | E19: =E18*E6 -> 330002400 | F19: =F18*F6 -> 632511000 | G19: =G18*G6 -> 1249992000
B22: Nota sobre o Ano 1:
B23: Múltiplos de ARR são pouco confiáveis com receita ainda pequena — para o valuation de HOJE (pré-lançamento),
B24: use as abas 'Berkus' e 'Scorecard', não este múltiplo. O Ano 1 aqui serve para visualizar a trajetória, não como
B25: referência de negociação imediata.
